justa/__init__.py
justa/__main__.py
justa/body.py
justa/clip.py
justa/colors.py
justa/core.py
justa/math_utils/__init__.py
justa/math_utils/domains.py
justa/math_utils/fields.py
justa/math_utils/functions.py
justa/math_utils/utils.py
justa-0.0.1.dev2.dist-info/LICENSE
justa-0.0.1.dev2.dist-info/METADATA
justa-0.0.1.dev2.dist-info/WHEEL
justa-0.0.1.dev2.dist-info/top_level.txt
justa-0.0.1.dev2.dist-info/RECORD
