Metadata-Version: 2.1
Name: justa
Version: 0.0.1.dev2
Summary: Just a simple plotting animator.
Home-page: https://github.com/eanorambuena/justa
Author: Emmanuel Norambuena
Author-email: eanorambuena@uc.cl
License: MIT
Project-URL: Bug Reports, https://github.com/eanorambuena/justa/issues
Project-URL: Source, https://github.com/eanorambuena/justa
Keywords: visualization,plotting
Classifier: Development Status :: 2 - Pre-Alpha
Classifier: Intended Audience :: Developers
Classifier: Topic :: Artistic Software
Classifier: Topic :: Multimedia :: Graphics :: Presentation
Classifier: Topic :: Scientific/Engineering :: Visualization
Classifier: Topic :: Software Development :: Libraries :: Python Modules
Classifier: Topic :: Utilities
Classifier: Natural Language :: English
Classifier: Operating System :: OS Independent
Classifier: Topic :: Multimedia :: Video
Classifier: License :: OSI Approved :: MIT License
Classifier: Programming Language :: Python :: 3
Classifier: Programming Language :: Python :: 3.5
Classifier: Programming Language :: Python :: 3.6
Classifier: Programming Language :: Python :: 3.7
Classifier: Programming Language :: Python :: 3.8
Classifier: Programming Language :: Python :: 3 :: Only
Requires-Python: >=3.5, <3.9
License-File: LICENSE
Requires-Dist: eggdriver (>=0.0.1)
Requires-Dist: pygame (<2.0.0)
Requires-Dist: moviepy
Requires-Dist: Colr
Requires-Dist: opencv-contrib-python
Requires-Dist: numpy
Requires-Dist: matplotlib
